pymbse/commons/__init__.py
pymbse/commons/schemas.py
pymbse_commons-0.1.3.dist-info/LICENSES/BSD-4-Clause.txt
pymbse_commons-0.1.3.dist-info/LICENSES/CC0-1.0.txt
pymbse_commons-0.1.3.dist-info/METADATA
pymbse_commons-0.1.3.dist-info/WHEEL
pymbse_commons-0.1.3.dist-info/RECORD
